MingxiangZhengnianShouce/Dockerfile
MingxiangZhengnianShouce/README.md
MingxiangZhengnianShouce/__init__.py
MingxiangZhengnianShouce/__main__.py
MingxiangZhengnianShouce/file.epub
MingxiangZhengnianShouce/index.html
MingxiangZhengnianShouce/css/__init__.py
MingxiangZhengnianShouce/css/annotations.css
MingxiangZhengnianShouce/css/main.css
MingxiangZhengnianShouce/css/normalize.css
MingxiangZhengnianShouce/css/popup.css
MingxiangZhengnianShouce/font/__init__.py
MingxiangZhengnianShouce/font/fontello.eot
MingxiangZhengnianShouce/font/fontello.svg
MingxiangZhengnianShouce/font/fontello.ttf
MingxiangZhengnianShouce/font/fontello.woff
MingxiangZhengnianShouce/img/__init__.py
MingxiangZhengnianShouce/img/annotator-glyph-sprite.png
MingxiangZhengnianShouce/img/annotator-icon-sprite.png
MingxiangZhengnianShouce/img/apple-touch-icon.png
MingxiangZhengnianShouce/img/cancelfullscreen.png
MingxiangZhengnianShouce/img/close.png
MingxiangZhengnianShouce/img/fullscreen.png
MingxiangZhengnianShouce/img/loader.gif
MingxiangZhengnianShouce/img/menu-icon.png
MingxiangZhengnianShouce/img/save.png
MingxiangZhengnianShouce/img/saved.png
MingxiangZhengnianShouce/img/settings-s.png
MingxiangZhengnianShouce/img/settings.png
MingxiangZhengnianShouce/img/star.png
MingxiangZhengnianShouce/js/__init__.py
MingxiangZhengnianShouce/js/epub.js
MingxiangZhengnianShouce/js/epub.min.js
MingxiangZhengnianShouce/js/epub.min.map
MingxiangZhengnianShouce/js/hooks.min.js
MingxiangZhengnianShouce/js/hooks.min.map
MingxiangZhengnianShouce/js/reader.js
MingxiangZhengnianShouce/js/reader.js.map
MingxiangZhengnianShouce/js/reader.min.js
MingxiangZhengnianShouce/js/reader.min.map
MingxiangZhengnianShouce/js/hooks/__init__.py
MingxiangZhengnianShouce/js/hooks/extensions/__init__.py
MingxiangZhengnianShouce/js/hooks/extensions/highlight.js
MingxiangZhengnianShouce/js/libs/__init__.py
MingxiangZhengnianShouce/js/libs/jquery.min.js
MingxiangZhengnianShouce/js/libs/localforage.min.js
mingxiang_zhengnian_shouce-2022.10.9.1.dist-info/METADATA
mingxiang_zhengnian_shouce-2022.10.9.1.dist-info/WHEEL
mingxiang_zhengnian_shouce-2022.10.9.1.dist-info/entry_points.txt
mingxiang_zhengnian_shouce-2022.10.9.1.dist-info/top_level.txt
mingxiang_zhengnian_shouce-2022.10.9.1.dist-info/RECORD
